agntcy_iomapper/__init__.py
agntcy_iomapper/agent/__init__.py
agntcy_iomapper/agent/agent_io_mapper.py
agntcy_iomapper/base/__init__.py
agntcy_iomapper/base/base.py
agntcy_iomapper/base/models.py
agntcy_iomapper/base/utils.py
agntcy_iomapper/imperative/__init__.py
agntcy_iomapper/imperative/imperative.py
agntcy_iomapper/langgraph/__init__.py
agntcy_iomapper/langgraph/create_langraph_iomapper.py
agntcy_iomapper/langgraph/langgraph.py
agntcy_iomapper/llamaindex/__init__.py
agntcy_iomapper/llamaindex/llamaindex.py
agntcy_iomapper/llamaindex/models.py
agntcy_iomapper/py.typed
agntcy_iomapper/pydantic_ai.py
agntcy_iomapper/version.py
agntcy_iomapper-0.2.3.dist-info/LICENSE
agntcy_iomapper-0.2.3.dist-info/METADATA
agntcy_iomapper-0.2.3.dist-info/WHEEL
agntcy_iomapper-0.2.3.dist-info/RECORD
