Metadata-Version: 2.3
Name: agntcy-iomapper
Version: 0.2.3
Summary: A tool to transform output from one agent to the input of another.
License: Apache-2.0
Author: AGNTCY Internet of Agents Collective
Author-email: pypi@agntcy.io
Maintainer: AGNTCY Internet of Agents Collective
Maintainer-email: pypi@agntcy.io
Requires-Python: >=3.9.0,<4.0
Classifier: License :: OSI Approved :: Apache Software License
Classifier: Programming Language :: Python :: 3
Classifier: Programming Language :: Python :: 3.9
Classifier: Programming Language :: Python :: 3.10
Classifier: Programming Language :: Python :: 3.11
Classifier: Programming Language :: Python :: 3.12
Classifier: Programming Language :: Python :: 3.13
Provides-Extra: langgraph
Provides-Extra: pydantic-ai
Requires-Dist: jinja2 (>=3.1.5,<4.0.0)
Requires-Dist: jsonpath-ng (>=1.7.0,<2.0.0)
Requires-Dist: jsonref (>=1.1.0,<2.0.0)
Requires-Dist: jsonschema[format] (>=4.23.0,<5.0.0)
Requires-Dist: langchain (>=0.3.19,<0.4.0) ; extra == "langgraph"
Requires-Dist: langchain-openai (>=0.3.6,<0.4.0) ; extra == "langgraph"
Requires-Dist: langgraph (>=0.3.16) ; extra == "langgraph"
Requires-Dist: llama-index (>=0.12.20,<0.13.0)
Requires-Dist: openapi-pydantic (>=0.5.1,<0.6.0)
Requires-Dist: pydantic (>=2.10.6,<3.0.0)
Requires-Dist: pydantic-ai (>=0.0.23,<0.0.24) ; extra == "pydantic-ai"
Requires-Dist: python-dotenv (>=1.0.1,<2.0.0)
Project-URL: Documentation, https://docs.agntcy.org/pages/semantic_sdk/io_mapper.html
Project-URL: Homepage, https://github.com/agntcy/iomapper-agnt
Project-URL: Issues, https://github.com/agntcy/iomapper-agnt/issues
Project-URL: Source, https://github.com/agntcy/iomapper-agnt
